validator903/__init__.py
validator903/config.py
validator903/datastore.py
validator903/ingress.py
validator903/report.py
validator903/types.py
validator903/util/__init__.py
validator903/utils.py
validator903/validator.py
validator903/validators.py
quality_lac_data_validator-1.0.3.dist-info/METADATA
quality_lac_data_validator-1.0.3.dist-info/WHEEL
quality_lac_data_validator-1.0.3.dist-info/LICENSE
quality_lac_data_validator-1.0.3.dist-info/RECORD
