Metadata-Version: 2.1
Name: quality-lac-data-validator
Version: 1.0.3
Summary: Shared module for validating the ruleset on the SSDA903 census using DfE rules.
Home-page: https://github.com/SocialFinanceDigitalLabs/quality-lac-data-beta-validator
License: MIT
Author: Mark Waddoups
Author-email: mark.waddoups@socialfinance.org.uk
Requires-Python: >=3.8,<4.0
Classifier: License :: OSI Approved :: MIT License
Classifier: Programming Language :: Python :: 3
Classifier: Programming Language :: Python :: 3.8
Classifier: Programming Language :: Python :: 3.9
Classifier: Programming Language :: Python :: 3.10
Classifier: Programming Language :: Python :: 3.11
Requires-Dist: numpy (==1.17.5)
Requires-Dist: openpyxl (>=3.0.9,<4.0.0)
Requires-Dist: pandas (==1.0.5)
Requires-Dist: quality-lac-data-ref-authorities (>=2021.4)
Requires-Dist: quality-lac-data-ref-postcodes (>=2021.8.1)
Requires-Dist: xlrd (>=2.0.1,<3.0.0)
Project-URL: Repository, https://github.com/SocialFinanceDigitalLabs/quality-lac-data-beta-validator
